tellius_data_manager/__init__.py
tellius_data_manager/alert_manager/__init__.py
tellius_data_manager/alert_manager/alert_manager.py
tellius_data_manager/alert_manager/alert_manager_factory.py
tellius_data_manager/alert_manager/chatops/__init__.py
tellius_data_manager/alert_manager/chatops/slack_alert_manager.py
tellius_data_manager/alert_manager/email/__init__.py
tellius_data_manager/alert_manager/email/email_alert_manager.py
tellius_data_manager/alert_manager/email/gmail_email_alert_manager.py
tellius_data_manager/alert_manager/email/outlook_email_alert_manager.py
tellius_data_manager/alert_manager/general/__init__.py
tellius_data_manager/alert_manager/general/null_alert_manager.py
tellius_data_manager/config_optional_factory.py
tellius_data_manager/config_reader/__init__.py
tellius_data_manager/config_reader/aws_secret_config_reader.py
tellius_data_manager/config_reader/config_reader.py
tellius_data_manager/config_reader/config_reader_factory.py
tellius_data_manager/config_reader/yaml_config_reader.py
tellius_data_manager/config_required_factory.py
tellius_data_manager/connectors/__init__.py
tellius_data_manager/connectors/connector.py
tellius_data_manager/connectors/connector_factory.py
tellius_data_manager/connectors/databases/__init__.py
tellius_data_manager/connectors/http/__init__.py
tellius_data_manager/connectors/http/rest_connector.py
tellius_data_manager/connectors/object_stores/__init__.py
tellius_data_manager/connectors/object_stores/object_store.py
tellius_data_manager/connectors/object_stores/s3.py
tellius_data_manager/errors/__init__.py
tellius_data_manager/errors/alert_error.py
tellius_data_manager/errors/tdm_error.py
tellius_data_manager/factory.py
tellius_data_manager/flows/__init__.py
tellius_data_manager/flows/flow.py
tellius_data_manager/flows/flow_builder.py
tellius_data_manager/flows/flow_manager.py
tellius_data_manager/logs/__init__.py
tellius_data_manager/logs/tellius_logger.py
tellius_data_manager/manage_data.py
tellius_data_manager-0.2.57.dist-info/LICENSE
tellius_data_manager-0.2.57.dist-info/WHEEL
tellius_data_manager-0.2.57.dist-info/METADATA
tellius_data_manager-0.2.57.dist-info/RECORD
