Metadata-Version: 2.1
Name: tellius-data-manager
Version: 0.2.57
Summary: 
Author: Tellius Open Source
Author-email: tellius.open.source@tellius.com
Requires-Python: >=3.9,<4.0
Classifier: Programming Language :: Python :: 3
Classifier: Programming Language :: Python :: 3.9
Classifier: Programming Language :: Python :: 3.10
Classifier: Programming Language :: Python :: 3.11
Requires-Dist: PyYAML (>=6.0,<7.0)
Requires-Dist: azure-storage-blob (>=12.13.1,<13.0.0)
Requires-Dist: boto3 (>=1.24.28,<2.0.0)
Requires-Dist: flatten-json (>=0.1.13,<0.2.0)
Requires-Dist: logging-json (>=0.2.1,<0.3.0)
Requires-Dist: pandas (>=1.4.3,<2.0.0)
Requires-Dist: providah (>=0.1.15.0,<0.2.0.0)
Requires-Dist: pyOpenSSL (>=22.0.0,<23.0.0)
Requires-Dist: requests (>=2.28.1,<3.0.0)
